examples/ltsteps_example.py
examples/ngspice_batch.py
examples/qspice_example.py
examples/raw_plotting.py
examples/raw_write_example.py
examples/run_montecarlo.py
examples/run_worst_case.py
examples/sim_client_example.py
examples/sim_runner_asc_example.py
examples/sim_runner_callback_example.py
examples/sim_runner_callback_process_example.py
examples/sim_runner_example.py
examples/sim_server_example.py
examples/sim_stepper_example.py
examples/spice_editor_example.py
spicelib/Histogram.py
spicelib/LTSteps.py
spicelib/__init__.py
spicelib/rawplot.py
spicelib/run_server.py
spicelib/client_server/__init__.py
spicelib/client_server/sim_client.py
spicelib/client_server/sim_server.py
spicelib/client_server/srv_sim_runner.py
spicelib/editor/asc_editor.py
spicelib/editor/base_editor.py
spicelib/editor/spice_editor.py
spicelib/log/__init__.py
spicelib/log/logfile_data.py
spicelib/log/ltsteps.py
spicelib/log/semi_dev_op_reader.py
spicelib/raw/__init__.py
spicelib/raw/raw_classes.py
spicelib/raw/raw_convert.py
spicelib/raw/raw_read.py
spicelib/raw/raw_write.py
spicelib/sim/__init__.py
spicelib/sim/process_callback.py
spicelib/sim/run_task.py
spicelib/sim/sim_runner.py
spicelib/sim/sim_stepping.py
spicelib/sim/simulator.py
spicelib/sim/tookit/__init__.py
spicelib/sim/tookit/failure_modes.py
spicelib/sim/tookit/montecarlo.py
spicelib/sim/tookit/sim_analysis.py
spicelib/sim/tookit/tolerance_deviations.py
spicelib/sim/tookit/worst_case.py
spicelib/simulators/__init__.py
spicelib/simulators/ltspice_simulator.py
spicelib/simulators/ngspice_simulator.py
spicelib/simulators/qspice_simulator.py
spicelib/simulators/xyce_simulator.py
spicelib/utils/detect_encoding.py
spicelib/utils/sweep_iterators.py
unittests/sweep_iterators_unittest.py
unittests/test_asc_editor.py
unittests/test_spicelib.py
newSpice-0.0.0.dist-info/LICENSE
newSpice-0.0.0.dist-info/METADATA
newSpice-0.0.0.dist-info/WHEEL
newSpice-0.0.0.dist-info/entry_points.txt
newSpice-0.0.0.dist-info/top_level.txt
newSpice-0.0.0.dist-info/RECORD
