Metadata-Version: 2.1
Name: newSpice
Version: 0.0.0
Summary: A NEW pythonic way to perform SPICE simulations.
Author-email: Robert Liang <lshy@mail.ustc.edu.cn>
License: GNU GENERAL PUBLIC LICENSE
Project-URL: Homepage, https://github.com/rliangcn/newSpice/
Project-URL: Based Project, https://github.com/nunobrum/spicelib/
Classifier: Programming Language :: Python :: 3
Classifier: License :: OSI Approved :: GNU General Public License v3 (GPLv3)
Classifier: Operating System :: OS Independent
Requires-Python: >=3.8
License-File: LICENSE
Requires-Dist: numpy
Requires-Dist: psutil
Requires-Dist: clipboard
Requires-Dist: matplotlib
Requires-Dist: keyboard
